pyley/__init__.py
pyley/pyley.py
tests/__init__.py
tests/test_cayley_client.py
tests/test_gizmo_query.py
pyley-0.2.2.2.dist-info/METADATA
pyley-0.2.2.2.dist-info/WHEEL
pyley-0.2.2.2.dist-info/top_level.txt
pyley-0.2.2.2.dist-info/RECORD
