Metadata-Version: 2.1
Name: pyley
Version: 0.2.2.2
Summary: Python client for an open-source graph database Cayley
Home-page: https://github.com/ziyasal/pyley
Author: Ziya SARIKAYA @ziyasal
Author-email: sarikayaziya@gmail.com
License: MIT License
Download-URL: https://pypi.org/pypi/pyley
Keywords: graph database,cayley,cayley python client,client
Platform: Any
Classifier: Intended Audience :: Developers
Classifier: License :: OSI Approved :: MIT License
Classifier: Operating System :: OS Independent
Classifier: Topic :: Software Development :: Libraries :: Python Modules
Classifier: Programming Language :: Python
Classifier: Programming Language :: Python :: 2.7
Classifier: Programming Language :: Python :: 3.3
Classifier: Programming Language :: Python :: 3.4
Classifier: Programming Language :: Python :: 3.5
Classifier: Programming Language :: Python :: 3.6
Requires-Dist: requests
